.pylintrc
tanzanite/README.md
tanzanite/__init__.py
tanzanite/__main__.py
tanzanite/backend/.gitignore
tanzanite/backend/app/.gitignore
tanzanite/backend/app/alembic/README
tanzanite/backend/app/alembic/__init__.py
tanzanite/backend/app/alembic/env.py
tanzanite/backend/app/alembic/script.py.mako
tanzanite/backend/app/alembic/versions/.keep
tanzanite/backend/app/alembic/versions/__init__.py
tanzanite/backend/app/alembic/versions/d4867f3a4c0a_first_revision.py
tanzanite/backend/app/alembic.ini
tanzanite/backend/app/app/__init__.py
tanzanite/backend/app/app/api/__init__.py
tanzanite/backend/app/app/api/deps.py
tanzanite/backend/app/app/api/v1/__init__.py
tanzanite/backend/app/app/api/v1/api.py
tanzanite/backend/app/app/api/v1/endpoints/__init__.py
tanzanite/backend/app/app/api/v1/endpoints/challenges.py
tanzanite/backend/app/app/api/v1/endpoints/login.py
tanzanite/backend/app/app/api/v1/endpoints/users.py
tanzanite/backend/app/app/api/v1/endpoints/utils.py
tanzanite/backend/app/app/backend_pre_start.py
tanzanite/backend/app/app/celeryworker_pre_start.py
tanzanite/backend/app/app/core/__init__.py
tanzanite/backend/app/app/core/celery_app.py
tanzanite/backend/app/app/crud/__init__.py
tanzanite/backend/app/app/crud/base.py
tanzanite/backend/app/app/crud/crud_challenge.py
tanzanite/backend/app/app/crud/crud_user.py
tanzanite/backend/app/app/db/__init__.py
tanzanite/backend/app/app/db/base.py
tanzanite/backend/app/app/db/base_class.py
tanzanite/backend/app/app/db/session.py
tanzanite/backend/app/app/db/tasks.py
tanzanite/backend/app/app/email-templates/src/new_account.mjml
tanzanite/backend/app/app/email-templates/src/reset_password.mjml
tanzanite/backend/app/app/email-templates/src/test_email.mjml
tanzanite/backend/app/app/main.py
tanzanite/backend/app/app/models/__init__.py
tanzanite/backend/app/app/models/challenge.py
tanzanite/backend/app/app/models/user.py
tanzanite/backend/app/app/schemas/__init__.py
tanzanite/backend/app/app/schemas/challenge.py
tanzanite-2022.3.1.dist-info/entry_points.txt
tanzanite-2022.3.1.dist-info/LICENSE.txt
tanzanite-2022.3.1.dist-info/WHEEL
tanzanite-2022.3.1.dist-info/METADATA
tanzanite-2022.3.1.dist-info/RECORD
