Metadata-Version: 2.1
Name: tanzanite
Version: 2022.3.1
Summary: An open source purpleteaming and CTF platform.
Home-page: https://github.com/davedittrich/tanzanite
License: Apache-2.0
Keywords: education,security,ctf,purpleteam,fastapi
Author: Dave Dittrich
Author-email: dave.dittrich@gmail.com
Maintainer: Dave Dittrich
Maintainer-email: dave.dittrich@gmail.com
Requires-Python: >=3.7,<4.0
Classifier: Development Status :: 2 - Pre-Alpha
Classifier: Environment :: Console
Classifier: Intended Audience :: Developers
Classifier: License :: OSI Approved :: Apache Software License
Classifier: Natural Language :: English
Classifier: Operating System :: OS Independent
Classifier: Programming Language :: Python
Classifier: Programming Language :: Python :: 3
Classifier: Programming Language :: Python :: 3.7
Classifier: Programming Language :: Python :: 3.8
Classifier: Programming Language :: Python :: 3.9
Classifier: Programming Language :: Python :: 3.10
Classifier: Programming Language :: Python :: 3
Classifier: Programming Language :: Python :: 3.7
Classifier: Programming Language :: Python :: 3.8
Classifier: Programming Language :: Python :: 3.9
Classifier: Topic :: Software Development
Classifier: Topic :: Utilities
Requires-Dist: Jinja2 (==2.11.3)
Requires-Dist: MarkupSafe (==2.0.1)
Requires-Dist: PyJWT (>=2.3.0,<3.0.0)
Requires-Dist: SQLAlchemy-Utils (>=0.38.1,<0.39.0)
Requires-Dist: Sphinx (>=4.3.2,<5.0.0)
Requires-Dist: aiofiles (>=0.8.0,<0.9.0)
Requires-Dist: alembic (>=1.4.2,<2.0.0)
Requires-Dist: celery (>=4.4.2,<5.0.0)
Requires-Dist: databases[postgresql,sqlite] (>=0.5.3,<0.6.0)
Requires-Dist: email-validator (>=1.0.5,<2.0.0)
Requires-Dist: emails (>=0.6,<0.7)
Requires-Dist: fastapi (>=0.54.1,<0.55.0)
Requires-Dist: gunicorn (>=20.0.4,<21.0.0)
Requires-Dist: httpx (>=0.22.0,<0.23.0)
Requires-Dist: isort (>=5.10.1,<6.0.0)
Requires-Dist: itsdangerous (>=2.1.0,<3.0.0)
Requires-Dist: jinja2 (>=2.11.2,<3.0.0)
Requires-Dist: passlib[bcrypt] (>=1.7.2,<2.0.0)
Requires-Dist: poetry2setup (>=1.0.0,<2.0.0)
Requires-Dist: psycopg2-binary (>=2.8.5,<3.0.0)
Requires-Dist: pydantic (>=1.9.0,<2.0.0)
Requires-Dist: pytest (>=5.4.1,<6.0.0)
Requires-Dist: python-dotenv (>=0.19.2,<0.20.0)
Requires-Dist: python-jose[cryptography] (>=3.1.0,<4.0.0)
Requires-Dist: python-multipart (>=0.0.5,<0.0.6)
Requires-Dist: python-secrets (>=22.1.0,<23.0.0)
Requires-Dist: raven (>=6.10.0,<7.0.0)
Requires-Dist: requests (>=2.23.0,<3.0.0)
Requires-Dist: setuptools (>=60.9.3,<61.0.0)
Requires-Dist: sphinx-rtd-theme (>=1.0.0,<2.0.0)
Requires-Dist: sqlalchemy (>=1.3.16,<2.0.0)
Requires-Dist: tenacity (>=6.1.0,<7.0.0)
Requires-Dist: uvicorn (>=0.17.1,<0.18.0)
Project-URL: Documentation, https://github.com/davedittrich/tanzanite
Project-URL: Repository, https://github.com/davedittrich/tanzanite
